<?xml version="1.0" encoding="UTF-8" ?>
<!DOCTYPE mapper PUBLIC "-//mybatis.org//DTD Mapper 3.0//EN" "http://mybatis.org/dtd/mybatis-3-mapper.dtd" >
<mapper namespace="com.gameloft9.demo.dataaccess.dao.system.TpTemplateMapper">

    <resultMap id="TempResultMap" type="com.gameloft9.demo.dataaccess.model.system.TpTemplate">
        <!--
          WARNING - @mbggenerated
          This element is automatically generated by MyBatis Generator, do not modify.
          This element was generated on Mon Dec 04 11:17:43 CST 2017.
        -->
        <id column="templateId" property="templateId" jdbcType="INTEGER" />
        <result column="bigTitleId" property="bigTitleId" jdbcType="INTEGER" />
        <result column="templateTitleId" property="templateTitleId" jdbcType="VARCHAR" />
        <result column="generateDate" property="generateDate" jdbcType="TIMESTAMP"/>
        <result column="id" property="id" jdbcType="INTEGER"/>

    </resultMap>
    <sql id="Temp_Column_List">
        <!--
          WARNING - @mbggenerated
          This element is automatically generated by MyBatis Generator, do not modify.
          This element was generated on Mon Dec 04 11:17:43 CST 2017.
        -->
        templateId,bigTitleId,templateTitleId,generateDate,id
    </sql>
    <select id="alltemp" resultMap="TempResultMap">
        SELECT
        t.templateId,
        t.templateTitleId,
        t.generateDate,
        res.resName id
        FROM
        tp_democratic_bigtitle AS b,
        tp_democratic_template AS t,
        tp_resourcelist AS res
        WHERE
        b.bigTitleId=t.bigTitleId
        AND
        t.id=res.id
        order by
        id desc,
        generateDate desc
        limit #{start,jdbcType=DECIMAL},#{end,jdbcType=DECIMAL}
    </select>
    <select id="counttemp" resultType="int" parameterType="map">
        <!--
          WARNING - @mbggenerated
          This element is automatically generated by MyBatis Generator, do not modify.
          This element was generated on Mon Dec 04 11:17:05 CST 2017.
        -->
        select
        count(1)
        from tp_democratic_record t
    </select>
    <insert id="insertbig" parameterType="com.gameloft9.demo.dataaccess.model.system.TpBigTitle" useGeneratedKeys="true" keyProperty="bigTitleId">
        insert into tp_democratic_bigtitle (bigTitle,`explain`,`number`)
        values (#{bigTitle},#{explain},#{number})
    </insert>

    <insert id="intsersubtitle" parameterType="com.gameloft9.demo.dataaccess.model.system.TpSubtitleContent" useGeneratedKeys="true" keyProperty="subtitleId">
        insert into tp_democratic_subtitlecontent (bigTitleId,subtitleContent)
        values (#{bigTitleId},#{subtitleContent})
    </insert>

    <insert id="intserstandard" parameterType="com.gameloft9.demo.dataaccess.model.system.TpStandard" useGeneratedKeys="true" keyProperty="standardId">
        insert into tp_democratic_standard (subtitleId,standardName,id)
        values (#{subtitleId},#{standardName},#{id})
    </insert>

    <insert id="intsersubstandard" parameterType="com.gameloft9.demo.dataaccess.model.system.TpSubstandard" useGeneratedKeys="true" keyProperty="substandardId">
        insert into tp_democratic_substandard (standardId,substandardName)
        values (#{standardId},#{substandardName})
    </insert>

    <insert id="insertpralation" parameterType="com.gameloft9.demo.dataaccess.model.system.TpRelationship" useGeneratedKeys="true" keyProperty="rid">
        insert into tp_democratic_relationship (subtitleId,uid)
        values (#{subtitleId},#{uid})
    </insert>
    <insert id="inserttem" parameterType="com.gameloft9.demo.dataaccess.model.system.TpTemplate" useGeneratedKeys="true" keyProperty="templateId">
        <!--
          WARNING - @mbggenerated
          This element is automatically generated by MyBatis Generator, do not modify.
          This element was generated on Mon Dec 04 11:17:05 CST 2017.
        -->
        insert into tp_democratic_template (bigTitleId,templateTitleId,generateDate,id)
        values (#{bigTitleId},#{templateTitleId},#{generateDate},#{id})
    </insert>
    <update id="qxzd" parameterType="com.gameloft9.demo.dataaccess.model.system.TpTemplate">
        <!--
          WARNING - @mbggenerated
          This element is automatically generated by MyBatis Generator, do not modify.
          This element was generated on Mon Dec 04 11:17:05 CST 2017.
        -->
        update tp_democratic_template
        set
        id = 53
        where templateTitleId = #{templateTitleId,jdbcType=VARCHAR}
    </update>
    <update id="zd" parameterType="com.gameloft9.demo.dataaccess.model.system.TpTemplate">
        <!--
          WARNING - @mbggenerated
          This element is automatically generated by MyBatis Generator, do not modify.
          This element was generated on Mon Dec 04 11:17:05 CST 2017.
        -->
        update tp_democratic_template
        set
        id = 52
        where templateTitleId = #{templateTitleId,jdbcType=VARCHAR}
    </update>
    <delete id="delete" parameterType="java.lang.Integer">
        <!--
          WARNING - @mbggenerated
          This element is automatically generated by MyBatis Generator, do not modify.
          This element was generated on Thu Dec 07 15:21:02 CST 2017.
        -->
        delete from tp_democratic_template
        where templateId = #{templateId,jdbcType=INTEGER}
    </delete>
    <select id="selectById" parameterType="Integer" resultType="java.lang.Integer">
        SELECT bigTitleId FROM  tp_democratic_template WHERE templateId=#{0}
    </select>
</mapper>
